pydreambrook/__init__.py
pydreambrook/cli.py
pydreambrook/pydreambrook.py
pydreambrook-0.1.0.dist-info/AUTHORS.rst
pydreambrook-0.1.0.dist-info/LICENSE
pydreambrook-0.1.0.dist-info/METADATA
pydreambrook-0.1.0.dist-info/WHEEL
pydreambrook-0.1.0.dist-info/entry_points.txt
pydreambrook-0.1.0.dist-info/top_level.txt
pydreambrook-0.1.0.dist-info/RECORD
