Metadata-Version: 2.1
Name: pydreambrook
Version: 0.1.0
Summary: Official Python Toolbox for DreamBrook Apps, Platforms, and Services
Home-page: https://github.com/dominikusbrian/pydreambrook
Author: Dominikus Brian
Author-email: domi@dominikusbrian.com
License: MIT license
Keywords: pydreambrook
Classifier: Development Status :: 2 - Pre-Alpha
Classifier: Intended Audience :: Developers
Classifier: License :: OSI Approved :: MIT License
Classifier: Natural Language :: English
Classifier: Programming Language :: Python :: 3
Classifier: Programming Language :: Python :: 3.6
Classifier: Programming Language :: Python :: 3.7
Classifier: Programming Language :: Python :: 3.8
Requires-Python: >=3.6
License-File: LICENSE
License-File: AUTHORS.rst
